compose_score.cp312-win_amd64.pyd
compose_score-0.2.3.dist-info/METADATA
compose_score-0.2.3.dist-info/WHEEL
compose_score-0.2.3.dist-info/top_level.txt
compose_score-0.2.3.dist-info/RECORD
