Metadata-Version: 2.1
Name: compose_score
Version: 0.2.3
Home-page: 
Author: 
Author-email: 
Platform: any
Requires-Dist: scipackage >=0.1.2
